souvenir/__init__.py
souvenir/base32.py
souvenir/id.py
souvenir_python-0.0.3.dist-info/LICENSE.md
souvenir_python-0.0.3.dist-info/METADATA
souvenir_python-0.0.3.dist-info/WHEEL
souvenir_python-0.0.3.dist-info/top_level.txt
souvenir_python-0.0.3.dist-info/RECORD
