Metadata-Version: 2.2
Name: souvenir-python
Version: 0.0.3
Summary: A tag identifier library based on https://github.com/j5pr/souvenir
Author-email: BriHan <brihan.tech@gmail.com>
License: MIT
Classifier: Development Status :: 5 - Production/Stable
Classifier: Intended Audience :: Developers
Classifier: License :: OSI Approved :: MIT License
Classifier: Programming Language :: Python :: 3
Requires-Python: >=3.10
License-File: LICENSE.md
Provides-Extra: dev
Requires-Dist: black==24.10.0; extra == "dev"
Requires-Dist: flake8==7.1.1; extra == "dev"
Requires-Dist: flake8-import-order==0.18.2; extra == "dev"
Requires-Dist: pytest==8.3.3; extra == "dev"
Requires-Dist: sphinx==8.1.3; extra == "dev"
Requires-Dist: sphinx_rtd_theme==3.0.2; extra == "dev"
Requires-Dist: twine==5.1.1; extra == "dev"
